AUTHORS.rst
CONTRIBUTING.rst
HISTORY.rst
LICENSE
MANIFEST.in
README.rst
setup.cfg
setup.py
Flask_NSQ.egg-info/PKG-INFO
Flask_NSQ.egg-info/SOURCES.txt
Flask_NSQ.egg-info/dependency_links.txt
Flask_NSQ.egg-info/not-zip-safe
Flask_NSQ.egg-info/requires.txt
Flask_NSQ.egg-info/top_level.txt
docs/Makefile
docs/authors.rst
docs/conf.py
docs/contributing.rst
docs/history.rst
docs/index.rst
docs/installation.rst
docs/make.bat
docs/readme.rst
docs/usage.rst
flask_nsq/__init__.py
flask_nsq/flask_nsq.py
tests/__init__.py
tests/integration_server.py
tests/test_flask_nsq.py