Metadata-Version: 1.1
Name: Flask-NSQ
Version: 0.1.0
Summary: Adds NSQ support for your Flask application
Home-page: https://github.com/nikhilkalige/flask-nsq
Author: Nikhil Kalige
Author-email: nikhilkalige@gmail.com
License: MIT
Keywords: flask-nsq
Platform: UNKNOWN
Classifier: Development Status :: 2 - Pre-Alpha
Classifier: Intended Audience :: Developers
Classifier: License :: OSI Approved :: MIT License
Classifier: Natural Language :: English
Classifier: Programming Language :: Python :: 2
Classifier: Programming Language :: Python :: 2.6
Classifier: Programming Language :: Python :: 2.7
Classifier: Programming Language :: Python :: 3
Classifier: Programming Language :: Python :: 3.3
Classifier: Programming Language :: Python :: 3.4
